<annotation>
        <folder>people_in_medical_masks</folder>
        <filename>372_mask.jpg</filename>
        <source>
            <database>people_in_medical_masks</database>
        </source>
        <size>
            <width>3000</width>
            <height>1941</height>
            <depth>3</depth>
        </size>
        <segmented>0</segmented>
    <object>
            <name>mask</name>
            <bndbox>
                <xmin>1529</xmin>
                <ymin>502</ymin>
                <xmax>1985</xmax>
                <ymax>1082</ymax>
            </bndbox>
        </object><object>
            <name>mask</name>
            <bndbox>
                <xmin>778</xmin>
                <ymin>610</ymin>
                <xmax>1185</xmax>
                <ymax>1059</ymax>
            </bndbox>
        </object><object>
            <name>mask</name>
            <bndbox>
                <xmin>236</xmin>
                <ymin>240</ymin>
                <xmax>467</xmax>
                <ymax>536</ymax>
            </bndbox>
        </object><object>
            <name>mask</name>
            <bndbox>
                <xmin>1919</xmin>
                <ymin>200</ymin>
                <xmax>2230</xmax>
                <ymax>534</ymax>
            </bndbox>
        </object><object>
            <name>mask</name>
            <bndbox>
                <xmin>1355</xmin>
                <ymin>13</ymin>
                <xmax>1487</xmax>
                <ymax>195</ymax>
            </bndbox>
        </object><object>
            <name>mask</name>
            <bndbox>
                <xmin>2625</xmin>
                <ymin>312</ymin>
                <xmax>2977</xmax>
                <ymax>704</ymax>
            </bndbox>
        </object></annotation>