<annotation>
        <folder>people_in_medical_masks</folder>
        <filename>422_mask.jpg</filename>
        <source>
            <database>people_in_medical_masks</database>
        </source>
        <size>
            <width>1280</width>
            <height>853</height>
            <depth>3</depth>
        </size>
        <segmented>0</segmented>
    <object>
            <name>mask</name>
            <bndbox>
                <xmin>537</xmin>
                <ymin>333</ymin>
                <xmax>890</xmax>
                <ymax>695</ymax>
            </bndbox>
        </object></annotation>