<annotation>
        <folder>people_in_medical_masks</folder>
        <filename>stsciRq.jpg</filename>
        <source>
            <database>people_in_medical_masks</database>
        </source>
        <size>
            <width>828</width>
            <height>1717</height>
            <depth>3</depth>
        </size>
        <segmented>0</segmented>
    <object>
            <name>mask</name>
            <bndbox>
                <xmin>249</xmin>
                <ymin>614</ymin>
                <xmax>535</xmax>
                <ymax>914</ymax>
            </bndbox>
        </object><object>
            <name>mask</name>
            <bndbox>
                <xmin>350</xmin>
                <ymin>1415</ymin>
                <xmax>503</xmax>
                <ymax>1571</ymax>
            </bndbox>
        </object></annotation>